<?xml version="1.0" encoding="utf-8" standalone="yes"?>
<Gesture Name="Custom_Points" timestamp="2015-July-28_11-39-39">
	<Stroke>
		<Point X="2.58117043006155" Y="241.666407990204" />
		<Point X="3.4468223620562" Y="240.78858692745" />
		<Point X="4.48985746408124" Y="239.411203336909" />
		<Point X="5.74409093741247" Y="237.744803058287" />
		<Point X="7.23381804440572" Y="235.685292996541" />
		<Point X="9.09257954258379" Y="233.623348324034" />
		<Point X="11.2495539905473" Y="231.92280123358" />
		<Point X="13.7115102359327" Y="230.427825341054" />
		<Point X="16.3985398332363" Y="229.397122070909" />
		<Point X="19.1005389144849" Y="228.744669425085" />
		<Point X="21.5712349834445" Y="228.564998889081" />
		<Point X="23.7008400096703" Y="228.95986701178" />
		<Point X="25.4031445497866" Y="229.972588139868" />
		<Point X="26.7592884132064" Y="231.642152762907" />
		<Point X="27.6053677647041" Y="233.790572249776" />
		<Point X="28.1308794570884" Y="236.396467340756" />
		<Point X="28.3971911659567" Y="239.488483060502" />
		<Point X="28.3496620852662" Y="242.697187896649" />
		<Point X="28.3474452128801" Y="246.220489361464" />
		<Point X="28.6043260737583" Y="249.820839609842" />
		<Point X="29.2023355565121" Y="253.413550995828" />
		<Point X="30.3593055121851" Y="257.023215272924" />
		<Point X="31.7222165578678" Y="260.370755957771" />
		<Point X="33.4562549865119" Y="263.270479473471" />
		<Point X="35.5435947032969" Y="265.722958566865" />
		<Point X="38.111930942693" Y="267.671486393586" />
		<Point X="40.8498917120365" Y="268.831260380132" />
		<Point X="43.8726647531621" Y="269.106738933453" />
		<Point X="46.9649874250406" Y="268.495959299296" />
		<Point X="50.1030166894125" Y="267.174439527374" />
		<Point X="53.3080414373482" Y="265.21416452502" />
		<Point X="56.3653304600327" Y="262.614850838031" />
		<Point X="59.4204469835478" Y="259.829155867437" />
		<Point X="62.3423519986746" Y="256.871380135124" />
		<Point X="65.1023688177718" Y="253.757623936359" />
		<Point X="67.9222144599267" Y="250.566370906355" />
		<Point X="70.743479797135" Y="247.47351972015" />
		<Point X="73.5308544659332" Y="244.378455759479" />
		<Point X="76.4715702604592" Y="241.476130378177" />
		<Point X="79.2654498165277" Y="239.17922849893" />
		<Point X="81.7678255347855" Y="237.762518401741" />
		<Point X="83.8967696612303" Y="237.351726368204" />
		<Point X="85.5379115966457" Y="237.875703955446" />
		<Point X="86.5322796469972" Y="239.297906481976" />
		<Point X="87.1078924137587" Y="241.789079962145" />
		<Point X="87.3047611304198" Y="245.155728072665" />
		<Point X="87.2948925563286" Y="249.150018729662" />
		<Point X="87.3175987672666" Y="253.516162855738" />
		<Point X="87.5026219074894" Y="258.137577897281" />
		<Point X="88.0439867269025" Y="262.526466470835" />
		<Point X="88.9795658177369" Y="266.5482197748" />
		<Point X="90.2305605346291" Y="270.158592107874" />
		<Point X="91.9492491482318" Y="273.17617665749" />
		<Point X="94.0495877001797" Y="275.355673871522" />
		<Point X="96.5586940614241" Y="276.761242367381" />
		<Point X="99.39807786519" Y="277.412074085902" />
		<Point X="102.493129014583" Y="277.355644460845" />
		<Point X="105.848316922687" Y="276.646537313377" />
		<Point X="109.237473368119" Y="275.301792933854" />
		<Point X="112.52475276667" Y="273.15283502001" />
		<Point X="115.795825583658" Y="270.475801656652" />
		<Point X="119.060195772446" Y="267.427828992613" />
		<Point X="122.117951563144" Y="263.884302099374" />
		<Point X="125.1093666909" Y="260.354469216138" />
		<Point X="128.06398555688" Y="256.812675239599" />
		<Point X="130.907755067811" Y="253.331060016415" />
		<Point X="133.611551006823" Y="250.209722674082" />
		<Point X="136.141252756459" Y="247.522805927801" />
		<Point X="138.375770934561" Y="245.401060555738" />
		<Point X="140.408764505089" Y="243.930488774541" />
		<Point X="142.069343643506" Y="243.312237677108" />
		<Point X="143.501085983239" Y="243.683229738499" />
		<Point X="144.696930352555" Y="244.768837028181" />
		<Point X="145.506621698492" Y="246.669912305924" />
		<Point X="146.210140581922" Y="249.191805368399" />
		<Point X="146.787525228343" Y="252.17478663014" />
		<Point X="147.246378620598" Y="255.394623037515" />
		<Point X="147.658091480221" Y="258.675742369002" />
		<Point X="148.332826922979" Y="261.866208168678" />
		<Point X="149.5187432936" Y="264.615769390572" />
		<Point X="151.066521527381" Y="267.052860524971" />
		<Point X="152.997586547024" Y="269.178145468934" />
		<Point X="155.324949334192" Y="270.544352509697" />
		<Point X="158.00466490731" Y="270.987455571166" />
		<Point X="160.930687166857" Y="270.659938341057" />
		<Point X="163.969548291258" Y="269.351477759676" />
		<Point X="167.123615524163" Y="267.211334260431" />
		<Point X="170.354404171822" Y="264.462479672628" />
		<Point X="173.487209231679" Y="261.117420700095" />
		<Point X="176.672472397461" Y="257.588253144962" />
		<Point X="179.940657671512" Y="253.803766701104" />
		<Point X="183.035559016672" Y="249.967403709865" />
		<Point X="186.167679701681" Y="246.141678546357" />
		<Point X="189.282156618761" Y="242.589988516322" />
		<Point X="192.270233477754" Y="239.537839111161" />
		<Point X="195.176058630223" Y="236.970142013208" />
		<Point X="197.812857582401" Y="235.110399441096" />
		<Point X="200.24794059838" Y="234.164011997174" />
		<Point X="202.451989145329" Y="234.067642265652" />
		<Point X="204.429087838844" Y="234.717299242735" />
		<Point X="206.160967861251" Y="236.36173102149" />
		<Point X="207.754674978824" Y="238.818685862791" />
		<Point X="209.296195476622" Y="242.047395534958" />
		<Point X="210.906545620358" Y="245.886637066146" />
		<Point X="212.617907549663" Y="249.845247713241" />
		<Point X="214.499691968245" Y="253.768420133398" />
		<Point X="216.690990783661" Y="257.297991063831" />
		<Point X="219.073014571195" Y="260.183449773931" />
		<Point X="221.859268479645" Y="262.389262421415" />
		<Point X="224.792977858658" Y="263.731190167814" />
		<Point X="228.080573846482" Y="264.268505707667" />
		<Point X="231.353171516585" Y="263.836778938855" />
		<Point X="234.796398957379" Y="262.509429104391" />
		<Point X="238.080592470816" Y="260.285167781327" />
		<Point X="241.095091726649" Y="257.289813181498" />
		<Point X="243.947865146987" Y="253.793872044492" />
		<Point X="246.60891237532" Y="249.882467090001" />
		<Point X="249.163266034276" Y="245.889922883291" />
		<Point X="251.613520022662" Y="241.863010776543" />
		<Point X="254.068909694186" Y="237.977299888026" />
		<Point X="256.506189637923" Y="234.432473300109" />
		<Point X="259.097541041823" Y="231.229020175206" />
		<Point X="261.645219166673" Y="228.627320484535" />
		<Point X="264.290715475439" Y="226.576586828494" />
		<Point X="266.602587198148" Y="225.243546281716" />
		<Point X="268.787040602078" Y="224.728875613872" />
		<Point X="270.655218600192" Y="225.183558744059" />
		<Point X="272.152522828626" Y="226.325958224866" />
		<Point X="273.299990082724" Y="228.456813415504" />
		<Point X="274.06151610267" Y="231.221187819178" />
		<Point X="274.690169633383" Y="234.913138653422" />
		<Point X="275.264466566408" Y="239.172499047842" />
		<Point X="275.899815976283" Y="243.600689258588" />
		<Point X="276.630549811668" Y="248.219516090692" />
		<Point X="277.773081243056" Y="252.687701860411" />
		<Point X="279.377381933804" Y="256.80286564099" />
		<Point X="281.29529709231" Y="260.395161871239" />
		<Point X="283.512816498635" Y="263.278793526093" />
		<Point X="286.042432113237" Y="265.361978629154" />
		<Point X="288.825878982651" Y="266.56810137424" />
		<Point X="291.82187187578" Y="266.980365373811" />
		<Point X="294.839938938338" Y="266.570498051757" />
		<Point X="297.987548121624" Y="265.347062984868" />
		<Point X="301.275565550542" Y="263.413853609623" />
		<Point X="304.527547380393" Y="260.92763064727" />
		<Point X="307.845390000911" Y="258.002101246312" />
		<Point X="311.175638076858" Y="254.696434503477" />
		<Point X="314.605614201679" Y="251.278595529742" />
		<Point X="318.044320646944" Y="248.005470559229" />
		<Point X="321.483260476918" Y="245.053087679583" />
		<Point X="324.844051628677" Y="242.366535219568" />
		<Point X="328.211758940176" Y="240.148529047485" />
		<Point X="331.406827201254" Y="238.518529196957" />
		<Point X="334.516338158337" Y="237.661465463786" />
		<Point X="337.57134112" Y="237.752401206006" />
		<Point X="340.388905890388" Y="238.707849114397" />
		<Point X="342.970284827593" Y="240.622995242395" />
		<Point X="345.401765837828" Y="243.385334340128" />
		<Point X="347.595337319539" Y="246.9517995846" />
		<Point X="349.480207321697" Y="251.110368389602" />
		<Point X="351.253364134606" Y="255.635116332946" />
		<Point X="352.932276690706" Y="260.212576426301" />
		<Point X="354.706948102228" Y="264.731280776823" />
		<Point X="356.661047839296" Y="268.81916696788" />
		<Point X="358.954663266719" Y="272.132679925758" />
		<Point X="361.414466122178" Y="274.52915479349" />
		<Point X="363.998945246568" Y="275.86307563474" />
		<Point X="366.713715745726" Y="275.983411473413" />
		<Point X="369.461337145595" Y="274.979714503199" />
		<Point X="372.345539255371" Y="272.935904523596" />
		<Point X="375.028890315215" Y="270.021230372254" />
		<Point X="377.650821224171" Y="266.415460262568" />
		<Point X="380.319917786055" Y="262.329442061599" />
		<Point X="382.976991716282" Y="257.925518190216" />
		<Point X="385.646759281123" Y="253.390554246489" />
		<Point X="388.523567756328" Y="248.7951915228" />
		<Point X="391.622132628198" Y="244.338451045807" />
		<Point X="394.843952379988" Y="240.293533902768" />
		<Point X="398.210322822997" Y="236.72469457532" />
		<Point X="401.522414468044" Y="233.751037271417" />
		<Point X="404.834179365685" Y="231.351246831649" />
		<Point X="407.974101568" Y="229.736115958048" />
		<Point X="413.478710483589" Y="229.493252449616" />
		<Point X="415.601176076663" Y="230.703682825841" />
		<Point X="417.354920663728" Y="232.799386021224" />
		<Point X="418.897061351483" Y="235.720913882137" />
		<Point X="420.156658179931" Y="239.151468569" />
		<Point X="421.319252699509" Y="242.871177072695" />
		<Point X="422.487721953675" Y="246.790498806393" />
		<Point X="423.685865805589" Y="250.676755068705" />
		<Point X="425.07111869331" Y="254.596644568412" />
		<Point X="426.637973018754" Y="258.503027326715" />
		<Point X="428.504423501219" Y="261.824331605405" />
		<Point X="430.56353704555" Y="264.440103684329" />
		<Point X="432.77564700135" Y="266.370725286973" />
		<Point X="435.090607504802" Y="267.449989320674" />
		<Point X="437.528329425201" Y="267.782499027497" />
		<Point X="440.223131640731" Y="267.339016555966" />
		<Point X="443.008635261351" Y="266.112773037669" />
		<Point X="445.908120609272" Y="264.156642204636" />
		<Point X="448.934663257587" Y="261.572809391113" />
		<Point X="452.092715201168" Y="258.600394579169" />
		<Point X="455.376354801963" Y="255.368853711813" />
		<Point X="458.686112854419" Y="252.111646104774" />
		<Point X="462.049669557657" Y="249.08825704592" />
		<Point X="465.469793887156" Y="246.386168725787" />
		<Point X="468.967436607874" Y="244.026079205502" />
		<Point X="472.548774815557" Y="242.005380093806" />
		<Point X="476.056659331078" Y="240.592136943795" />
		<Point X="479.2585389108" Y="240.042698864401" />
		<Point X="482.098523522498" Y="240.454194469336" />
		<Point X="484.027292724644" Y="241.225891265903" />
		<Point X="484.930549211337" Y="242.432495379603" />
		<Point X="484.682344914131" Y="243.770807029951" />
		<Point X="483.288652631624" Y="244.986707164361" />
		<Point X="480.360380836801" Y="245.913139672394" />
	</Stroke>
</Gesture>
