<?xml version="1.0" encoding="utf-8"?>
<Gesture xmlns:xsd="http://www.w3.org/2001/XMLSchema" xmlns:xsi="http://www.w3.org/2001/XMLSchema-instance">
  <Name>Cosine</Name>
  <Subject>Erick</Subject>
  <Iteration>4</Iteration>
  <InputType>Leap Motion</InputType>
  <Speed>MEDIUM</Speed>
  <time>2513297</time>
  <NumPts>270</NumPts>
  <Stroke Index="1">
    <Point X="3.2142333984375" Y="345.735595703125" Z="87.926017761230469" T="83351994790" />
    <Point X="3.02459716796875" Y="345.28622436523437" Z="87.881965637207031" T="83352004136" />
    <Point X="2.4634246826171875" Y="345.08251953125" Z="87.826774597167969" T="83352013482" />
    <Point X="1.7877960205078125" Y="344.94012451171875" Z="87.728668212890625" T="83352022827" />
    <Point X="1.352325439453125" Y="344.82015991210937" Z="87.747329711914063" T="83352032168" />
    <Point X="1.0573959350585937" Y="344.77963256835937" Z="87.7567367553711" T="83352041503" />
    <Point X="0.77254486083984375" Y="344.65960693359375" Z="87.780441284179688" T="83352050849" />
    <Point X="0.58669281005859375" Y="344.60476684570312" Z="87.7291488647461" T="83352060195" />
    <Point X="0.43674468994140625" Y="344.42141723632812" Z="87.685859680175781" T="83352069540" />
    <Point X="0.3258819580078125" Y="344.20242309570312" Z="87.64508056640625" T="83352078886" />
    <Point X="0.238067626953125" Y="344.0252685546875" Z="87.644180297851563" T="83352088231" />
    <Point X="0" Y="343.20120239257812" Z="87.605178833007813" T="83352097577" />
    <Point X="0.06224822998046875" Y="342.25210571289062" Z="87.627738952636719" T="83352106923" />
    <Point X="0.69075775146484375" Y="341.74795532226562" Z="87.353309631347656" T="83352116263" />
    <Point X="1.038970947265625" Y="340.76544189453125" Z="87.273345947265625" T="83352125609" />
    <Point X="1.5819549560546875" Y="339.56231689453125" Z="87.2428970336914" T="83352134949" />
    <Point X="2.7704010009765625" Y="337.63748168945312" Z="87.1759033203125" T="83352144295" />
    <Point X="3.522857666015625" Y="336.41940307617187" Z="87.10186767578125" T="83352153636" />
    <Point X="4.085693359375" Y="335.776611328125" Z="86.995407104492188" T="83352162981" />
    <Point X="5.1220321655273438" Y="334.8101806640625" Z="86.965133666992188" T="83352172327" />
    <Point X="5.6402130126953125" Y="332.5042724609375" Z="86.0026626586914" T="83352181672" />
    <Point X="6.7719650268554687" Y="331.95620727539062" Z="86.13934326171875" T="83352191018" />
    <Point X="8.0445098876953125" Y="329.77783203125" Z="86.6946792602539" T="83352200364" />
    <Point X="9.2078628540039062" Y="329.10198974609375" Z="86.581382751464844" T="83352209709" />
    <Point X="10.72314453125" Y="328.62396240234375" Z="86.624496459960938" T="83352219055" />
    <Point X="12.94232177734375" Y="328.75735473632812" Z="86.523323059082031" T="83352228395" />
    <Point X="14.143730163574219" Y="328.52041625976562" Z="86.306915283203125" T="83352237741" />
    <Point X="15.311172485351562" Y="328.96456909179687" Z="85.840660095214844" T="83352247077" />
    <Point X="17.2435302734375" Y="328.41537475585938" Z="86.130691528320313" T="83352256417" />
    <Point X="18.888473510742188" Y="327.3516845703125" Z="86.480751037597656" T="83352265758" />
    <Point X="20.219253540039063" Y="327.65814208984375" Z="85.9197769165039" T="83352275098" />
    <Point X="21.355781555175781" Y="328.02963256835937" Z="85.493354797363281" T="83352284439" />
    <Point X="22.962318420410156" Y="328.98779296875" Z="85.721275329589844" T="83352293780" />
    <Point X="24.772804260253906" Y="330.91433715820312" Z="86.243301391601563" T="83352303125" />
    <Point X="26.562522888183594" Y="332.29934692382812" Z="86.17822265625" T="83352312466" />
    <Point X="27.94635009765625" Y="333.32760620117187" Z="86.006477355957031" T="83352321806" />
    <Point X="30.079139709472656" Y="336.5526123046875" Z="85.377029418945313" T="83352331152" />
    <Point X="31.958908081054688" Y="338.77578735351562" Z="85.010337829589844" T="83352340493" />
    <Point X="34.238334655761719" Y="340.63360595703125" Z="84.6768798828125" T="83352349838" />
    <Point X="35.759078979492187" Y="343.12741088867188" Z="85.294952392578125" T="83352359179" />
    <Point X="36.975440979003906" Y="345.59231567382812" Z="85.39898681640625" T="83352368524" />
    <Point X="38.894882202148438" Y="349.36471557617187" Z="85.748817443847656" T="83352377870" />
    <Point X="40.274444580078125" Y="351.3631591796875" Z="86.640853881835938" T="83352387216" />
    <Point X="41.661750793457031" Y="354.08477783203125" Z="86.9594955444336" T="83352396556" />
    <Point X="43.026809692382813" Y="356.97488403320312" Z="85.068679809570313" T="83352405897" />
    <Point X="44.080490112304688" Y="358.7623291015625" Z="84.029037475585937" T="83352415237" />
    <Point X="45.310775756835938" Y="361.40350341796875" Z="83.9083480834961" T="83352424583" />
    <Point X="47.108345031738281" Y="364.95382690429687" Z="83.571846008300781" T="83352433924" />
    <Point X="48.480758666992188" Y="368.2247314453125" Z="83.4942855834961" T="83352443269" />
    <Point X="49.476722717285156" Y="371.81365966796875" Z="83.345001220703125" T="83352452615" />
    <Point X="50.346405029296875" Y="374.87112426757812" Z="83.221809387207031" T="83352461960" />
    <Point X="51.336563110351563" Y="378.84112548828125" Z="82.6158218383789" T="83352471301" />
    <Point X="52.263160705566406" Y="381.83499145507812" Z="82.237579345703125" T="83352480642" />
    <Point X="53.623985290527344" Y="386.23861694335937" Z="81.905349731445313" T="83352489987" />
    <Point X="54.832809448242188" Y="391.30075073242187" Z="80.003875732421875" T="83352499328" />
    <Point X="55.728775024414063" Y="395.79217529296875" Z="78.726615905761719" T="83352508668" />
    <Point X="56.672195434570312" Y="399.106201171875" Z="78.138359069824219" T="83352518014" />
    <Point X="57.556198120117188" Y="402.01766967773437" Z="77.933799743652344" T="83352527360" />
    <Point X="58.5140380859375" Y="405.48843383789062" Z="77.466720581054687" T="83352536705" />
    <Point X="59.330665588378906" Y="408.64376831054687" Z="77.321769714355469" T="83352546051" />
    <Point X="60.260581970214844" Y="412.45257568359375" Z="77.576820373535156" T="83352555396" />
    <Point X="61.256496429443359" Y="415.93585205078125" Z="77.76678466796875" T="83352564742" />
    <Point X="62.255268096923828" Y="419.69924926757812" Z="77.5115737915039" T="83352574088" />
    <Point X="63.022560119628906" Y="423.62771606445312" Z="76.837509155273438" T="83352583433" />
    <Point X="63.632171630859375" Y="426.91171264648437" Z="76.063552856445312" T="83352592779" />
    <Point X="64.633808135986328" Y="430.68161010742187" Z="76.017005920410156" T="83352602124" />
    <Point X="65.319625854492188" Y="434.39495849609375" Z="76.459365844726563" T="83352611470" />
    <Point X="66.593414306640625" Y="439.13296508789062" Z="76.658012390136719" T="83352620816" />
    <Point X="67.358489990234375" Y="441.39013671875" Z="76.874992370605469" T="83352630156" />
    <Point X="68.015956878662109" Y="443.67144775390625" Z="76.311843872070313" T="83352639497" />
    <Point X="68.738296508789063" Y="446.04708862304688" Z="76.365425109863281" T="83352648842" />
    <Point X="69.513362884521484" Y="447.95529174804688" Z="76.01611328125" T="83352658188" />
    <Point X="70.441127777099609" Y="450.63601684570312" Z="75.6856460571289" T="83352667534" />
    <Point X="71.2715835571289" Y="453.4371337890625" Z="75.42510986328125" T="83352676874" />
    <Point X="72.470748901367188" Y="456.190673828125" Z="75.173263549804688" T="83352686215" />
    <Point X="73.651020050048828" Y="458.23422241210937" Z="75.160453796386719" T="83352695560" />
    <Point X="74.580883026123047" Y="459.7325439453125" Z="74.942176818847656" T="83352704906" />
    <Point X="75.569717407226563" Y="461.20718383789062" Z="74.6716537475586" T="83352714252" />
    <Point X="76.450965881347656" Y="462.54312133789062" Z="74.414093017578125" T="83352723592" />
    <Point X="77.2192268371582" Y="463.220458984375" Z="74.260734558105469" T="83352732938" />
    <Point X="78.161727905273437" Y="464.22979736328125" Z="74.060371398925781" T="83352742283" />
    <Point X="79.059001922607422" Y="464.78732299804687" Z="73.918426513671875" T="83352751624" />
    <Point X="79.8997917175293" Y="465.0318603515625" Z="73.858779907226563" T="83352760965" />
    <Point X="81.0074691772461" Y="465.09848022460937" Z="73.910682678222656" T="83352770310" />
    <Point X="82.11627197265625" Y="464.955810546875" Z="73.78167724609375" T="83352779656" />
    <Point X="83.296230316162109" Y="464.66787719726562" Z="73.932807922363281" T="83352788996" />
    <Point X="84.598995208740234" Y="464.0128173828125" Z="73.918815612792969" T="83352798342" />
    <Point X="85.606887817382812" Y="463.049072265625" Z="73.918571472167969" T="83352807688" />
    <Point X="86.826850891113281" Y="461.85418701171875" Z="73.885848999023437" T="83352817033" />
    <Point X="87.880455017089844" Y="460.07571411132812" Z="74.246055603027344" T="83352826379" />
    <Point X="88.820743560791016" Y="458.4122314453125" Z="74.181587219238281" T="83352835719" />
    <Point X="90.191650390625" Y="455.33392333984375" Z="74.9596939086914" T="83352845065" />
    <Point X="91.26325798034668" Y="452.01174926757812" Z="74.7521743774414" T="83352854411" />
    <Point X="92.10740852355957" Y="449.77642822265625" Z="74.716888427734375" T="83352863751" />
    <Point X="93.264322280883789" Y="447.54495239257812" Z="74.850166320800781" T="83352873097" />
    <Point X="94.287960052490234" Y="444.51602172851562" Z="75.541732788085938" T="83352882437" />
    <Point X="95.058757781982422" Y="441.5435791015625" Z="76.246109008789063" T="83352891783" />
    <Point X="95.901889801025391" Y="437.8157958984375" Z="76.924354553222656" T="83352901124" />
    <Point X="96.365962982177734" Y="434.52603149414062" Z="76.768272399902344" T="83352910469" />
    <Point X="96.848239898681641" Y="431.67343139648437" Z="76.7525634765625" T="83352919815" />
    <Point X="97.489250183105469" Y="428.60122680664062" Z="76.530021667480469" T="83352929160" />
    <Point X="97.753934860229492" Y="426.08883666992187" Z="76.4779052734375" T="83352938506" />
    <Point X="98.120317459106445" Y="421.76620483398438" Z="76.514358520507812" T="83352947847" />
    <Point X="98.657663345336914" Y="417.92974853515625" Z="77.076980590820313" T="83352957187" />
    <Point X="99.219106674194336" Y="413.62640380859375" Z="78.133407592773437" T="83352966533" />
    <Point X="99.617591857910156" Y="410.26547241210937" Z="77.905143737792969" T="83352975878" />
    <Point X="99.9448299407959" Y="407.6097412109375" Z="77.567375183105469" T="83352985224" />
    <Point X="100.18098258972168" Y="402.985595703125" Z="78.223945617675781" T="83352994570" />
    <Point X="100.59200668334961" Y="399.57635498046875" Z="78.598220825195312" T="83353003910" />
    <Point X="101.04142951965332" Y="396.90167236328125" Z="78.759223937988281" T="83353013256" />
    <Point X="101.32225036621094" Y="392.7723388671875" Z="79.012298583984375" T="83353022596" />
    <Point X="101.71292877197266" Y="389.51947021484375" Z="79.8553237915039" T="83353031942" />
    <Point X="102.24196243286133" Y="387.14569091796875" Z="79.850677490234375" T="83353041288" />
    <Point X="102.69070816040039" Y="384.01153564453125" Z="80.8120346069336" T="83353050633" />
    <Point X="103.19777679443359" Y="380.13204956054687" Z="81.954795837402344" T="83353059969" />
    <Point X="103.74350738525391" Y="375.889892578125" Z="82.46917724609375" T="83353069314" />
    <Point X="104.15741729736328" Y="372.3328857421875" Z="83.01678466796875" T="83353078660" />
    <Point X="104.74567222595215" Y="369.22802734375" Z="83.833786010742188" T="83353088006" />
    <Point X="105.43278026580811" Y="366.13967895507812" Z="85.405632019042969" T="83353097346" />
    <Point X="106.18916416168213" Y="362.0631103515625" Z="86.310127258300781" T="83353106692" />
    <Point X="107.15154933929443" Y="359.18865966796875" Z="86.998382568359375" T="83353116037" />
    <Point X="107.83174514770508" Y="356.92868041992187" Z="87.549346923828125" T="83353125383" />
    <Point X="108.50475215911865" Y="353.58535766601562" Z="87.703262329101563" T="83353134729" />
    <Point X="109.27134037017822" Y="350.3658447265625" Z="87.582443237304688" T="83353144074" />
    <Point X="110.00400733947754" Y="348.6290283203125" Z="87.025894165039063" T="83353153415" />
    <Point X="110.90025997161865" Y="347.978759765625" Z="87.743232727050781" T="83353162755" />
    <Point X="111.64371204376221" Y="346.6424560546875" Z="87.706192016601562" T="83353172101" />
    <Point X="112.60941123962402" Y="344.7353515625" Z="86.984489440917969" T="83353181447" />
    <Point X="113.6390438079834" Y="343.68316650390625" Z="86.367935180664063" T="83353190792" />
    <Point X="114.71083068847656" Y="342.85641479492187" Z="85.8052749633789" T="83353200138" />
    <Point X="115.68059062957764" Y="341.68310546875" Z="84.729629516601563" T="83353209483" />
    <Point X="116.55466747283936" Y="341.5340576171875" Z="84.031913757324219" T="83353218829" />
    <Point X="117.39545106887817" Y="341.84234619140625" Z="83.726226806640625" T="83353228170" />
    <Point X="118.74334239959717" Y="342.3662109375" Z="82.942886352539062" T="83353237510" />
    <Point X="120.03834962844849" Y="342.10195922851562" Z="83.771171569824219" T="83353246851" />
    <Point X="121.02587586641312" Y="342.3323974609375" Z="84.2655029296875" T="83353256186" />
    <Point X="122.29775655269623" Y="342.06539916992187" Z="84.418563842773438" T="83353265522" />
    <Point X="123.53662753105164" Y="342.97006225585937" Z="85.025039672851562" T="83353274858" />
    <Point X="124.97394180297852" Y="343.60903930664062" Z="85.02001953125" T="83353284198" />
    <Point X="126.19069004058838" Y="344.6192626953125" Z="85.500350952148438" T="83353293534" />
    <Point X="127.36998987197876" Y="345.87295532226562" Z="85.682579040527344" T="83353302869" />
    <Point X="128.74768018722534" Y="347.37088012695312" Z="86.519866943359375" T="83353312205" />
    <Point X="129.93420886993408" Y="348.359619140625" Z="86.859458923339844" T="83353321551" />
    <Point X="131.16375637054443" Y="349.75299072265625" Z="86.4437026977539" T="83353330891" />
    <Point X="132.32229709625244" Y="350.82449340820312" Z="85.498603820800781" T="83353340237" />
    <Point X="133.50507926940918" Y="353.10934448242187" Z="85.916854858398438" T="83353349582" />
    <Point X="134.75817012786865" Y="356.0972900390625" Z="87.149711608886719" T="83353358923" />
    <Point X="135.97820281982422" Y="357.28439331054687" Z="86.993545532226563" T="83353368259" />
    <Point X="137.05556011199951" Y="359.06454467773437" Z="86.799232482910156" T="83353377604" />
    <Point X="138.27048492431641" Y="362.31414794921875" Z="86.83978271484375" T="83353386950" />
    <Point X="139.46284103393555" Y="364.11160278320313" Z="84.7900390625" T="83353396295" />
    <Point X="140.15531349182129" Y="366.19586181640625" Z="84.389266967773438" T="83353405631" />
    <Point X="140.91884231567383" Y="368.51864624023437" Z="84.9556655883789" T="83353414977" />
    <Point X="141.9547004699707" Y="371.96316528320313" Z="85.372589111328125" T="83353424322" />
    <Point X="143.01046562194824" Y="375.58645629882812" Z="85.062065124511719" T="83353433668" />
    <Point X="143.99895095825195" Y="378.42593383789062" Z="84.545982360839844" T="83353443008" />
    <Point X="144.88149070739746" Y="380.7789306640625" Z="85.1815185546875" T="83353452354" />
    <Point X="145.90969657897949" Y="383.20431518554687" Z="85.4534912109375" T="83353461700" />
    <Point X="146.47949409484863" Y="386.6370849609375" Z="86.515907287597656" T="83353471045" />
    <Point X="147.39254760742187" Y="389.54171752929687" Z="86.666954040527344" T="83353480391" />
    <Point X="148.34402656555176" Y="392.9234619140625" Z="86.010902404785156" T="83353489736" />
    <Point X="149.27671432495117" Y="395.8013916015625" Z="85.3854751586914" T="83353499077" />
    <Point X="150.18198013305664" Y="399.65280151367187" Z="85.140083312988281" T="83353508423" />
    <Point X="151.002197265625" Y="403.151123046875" Z="85.974609375" T="83353517768" />
    <Point X="151.78536415100098" Y="405.9205322265625" Z="85.814002990722656" T="83353527114" />
    <Point X="152.56447219848633" Y="408.97152709960937" Z="85.587158203125" T="83353536454" />
    <Point X="153.41813278198242" Y="411.78842163085937" Z="84.784835815429688" T="83353545800" />
    <Point X="154.27754592895508" Y="414.15008544921875" Z="84.407073974609375" T="83353555146" />
    <Point X="155.31398391723633" Y="417.53082275390625" Z="84.171867370605469" T="83353564491" />
    <Point X="156.23167037963867" Y="420.23837280273437" Z="83.9555435180664" T="83353573832" />
    <Point X="157.18312072753906" Y="423.2259521484375" Z="83.021331787109375" T="83353583172" />
    <Point X="158.08574295043945" Y="426.03466796875" Z="82.7603530883789" T="83353592518" />
    <Point X="159.05653381347656" Y="428.0390625" Z="82.630355834960937" T="83353601859" />
    <Point X="159.85020065307617" Y="430.01449584960937" Z="82.478530883789063" T="83353611199" />
    <Point X="160.6882438659668" Y="432.88809204101562" Z="81.88580322265625" T="83353620545" />
    <Point X="161.90571975708008" Y="435.27267456054687" Z="81.233749389648438" T="83353629885" />
    <Point X="162.93481826782227" Y="437.39346313476562" Z="80.990928649902344" T="83353639231" />
    <Point X="163.87115478515625" Y="440.41494750976563" Z="81.14666748046875" T="83353648577" />
    <Point X="164.90521621704102" Y="442.25772094726562" Z="80.24151611328125" T="83353657922" />
    <Point X="165.77529144287109" Y="444.34115600585937" Z="79.63421630859375" T="83353667268" />
    <Point X="166.79898071289062" Y="446.07293701171875" Z="79.043807983398438" T="83353676613" />
    <Point X="167.95340728759766" Y="447.6334228515625" Z="78.876815795898437" T="83353685954" />
    <Point X="168.97237014770508" Y="449.1446533203125" Z="78.598564147949219" T="83353695295" />
    <Point X="169.96271133422852" Y="450.6490478515625" Z="78.521934509277344" T="83353704635" />
    <Point X="170.95530319213867" Y="451.7515869140625" Z="78.256820678710937" T="83353713981" />
    <Point X="172.04728698730469" Y="452.86209106445312" Z="78.321060180664063" T="83353723326" />
    <Point X="173.16266632080078" Y="453.6923828125" Z="78.300201416015625" T="83353732672" />
    <Point X="174.19022750854492" Y="454.49649047851562" Z="78.350791931152344" T="83353742013" />
    <Point X="175.13501739501953" Y="455.1435546875" Z="78.3344955444336" T="83353751358" />
    <Point X="176.20755386352539" Y="455.74661254882812" Z="78.302520751953125" T="83353760704" />
    <Point X="177.44091033935547" Y="456.33685302734375" Z="78.003143310546875" T="83353770049" />
    <Point X="178.37106323242187" Y="456.62588500976562" Z="77.836418151855469" T="83353779390" />
    <Point X="179.49091720581055" Y="456.72488403320312" Z="77.758132934570312" T="83353788736" />
    <Point X="180.57808303833008" Y="456.34182739257812" Z="78.052322387695313" T="83353798081" />
    <Point X="181.64174270629883" Y="456.01889038085937" Z="78.29833984375" T="83353807427" />
    <Point X="182.8853874206543" Y="455.364990234375" Z="78.687385559082031" T="83353816767" />
    <Point X="184.06943511962891" Y="454.10708618164062" Z="79.107376098632813" T="83353826113" />
    <Point X="185.21675872802734" Y="452.86117553710937" Z="79.377159118652344" T="83353835459" />
    <Point X="186.26004028320312" Y="451.78244018554687" Z="79.525680541992188" T="83353844804" />
    <Point X="187.34415435791016" Y="450.10775756835937" Z="79.528701782226563" T="83353854145" />
    <Point X="188.32177734375" Y="448.28884887695312" Z="79.554702758789063" T="83353863490" />
    <Point X="189.33435821533203" Y="446.38278198242187" Z="79.495292663574219" T="83353872836" />
    <Point X="190.29343414306641" Y="444.0859375" Z="78.804229736328125" T="83353882182" />
    <Point X="191.23665618896484" Y="441.97232055664062" Z="78.593109130859375" T="83353891522" />
    <Point X="192.02447509765625" Y="439.556396484375" Z="78.923553466796875" T="83353900863" />
    <Point X="192.88465881347656" Y="436.77471923828125" Z="79.908897399902344" T="83353910208" />
    <Point X="193.882080078125" Y="433.19845581054687" Z="81.036758422851563" T="83353919554" />
    <Point X="194.79050445556641" Y="429.91021728515625" Z="81.541397094726563" T="83353928895" />
    <Point X="195.49176025390625" Y="426.2677001953125" Z="81.883232116699219" T="83353938240" />
    <Point X="196.00192260742187" Y="423.33685302734375" Z="82.612129211425781" T="83353947586" />
    <Point X="196.5584716796875" Y="420.076416015625" Z="84.119354248046875" T="83353956931" />
    <Point X="197.19772338867187" Y="416.35540771484375" Z="85.30340576171875" T="83353966272" />
    <Point X="197.69459533691406" Y="413.55215454101562" Z="85.772666931152344" T="83353975618" />
    <Point X="198.32810211181641" Y="409.9945068359375" Z="85.878471374511719" T="83353984963" />
    <Point X="198.56088256835937" Y="406.606201171875" Z="86.7129898071289" T="83353994309" />
    <Point X="199.07159423828125" Y="402.65185546875" Z="88.174110412597656" T="83354003649" />
    <Point X="199.59854888916016" Y="399.13720703125" Z="88.950721740722656" T="83354012995" />
    <Point X="199.96521759033203" Y="395.93853759765625" Z="87.7830581665039" T="83354022341" />
    <Point X="200.29611968994141" Y="392.5174560546875" Z="88.9822006225586" T="83354031686" />
    <Point X="200.60652160644531" Y="388.93060302734375" Z="90.323860168457031" T="83354041027" />
    <Point X="201.0662841796875" Y="385.3424072265625" Z="92.067787170410156" T="83354050372" />
    <Point X="201.56611633300781" Y="381.4405517578125" Z="92.248542785644531" T="83354059718" />
    <Point X="202.13758850097656" Y="377.990966796875" Z="93.136138916015625" T="83354069064" />
    <Point X="202.44050598144531" Y="374.94967651367187" Z="93.782295227050781" T="83354078404" />
    <Point X="202.60102081298828" Y="372.204833984375" Z="94.4927749633789" T="83354087750" />
    <Point X="203.50807189941406" Y="367.08892822265625" Z="92.860519409179687" T="83354097090" />
    <Point X="204.12107086181641" Y="363.25009155273437" Z="93.3674545288086" T="83354106436" />
    <Point X="204.68983459472656" Y="359.9788818359375" Z="93.858688354492188" T="83354115777" />
    <Point X="205.40210723876953" Y="357.2967529296875" Z="94.06817626953125" T="83354125122" />
    <Point X="206.07331848144531" Y="354.31976318359375" Z="93.539337158203125" T="83354134468" />
    <Point X="206.89532470703125" Y="351.76174926757812" Z="93.644546508789063" T="83354143813" />
    <Point X="207.29628753662109" Y="348.54901123046875" Z="93.976165771484375" T="83354153159" />
    <Point X="207.84342956542969" Y="345.34271240234375" Z="94.0187759399414" T="83354162500" />
    <Point X="208.68115234375" Y="342.5843505859375" Z="94.660293579101563" T="83354171840" />
    <Point X="209.43978118896484" Y="340.43341064453125" Z="95.296218872070312" T="83354181186" />
    <Point X="210.46503448486328" Y="336.71957397460938" Z="96.384025573730469" T="83354190526" />
    <Point X="211.35251617431641" Y="333.42767333984375" Z="95.607109069824219" T="83354199872" />
    <Point X="211.84660339355469" Y="332.12701416015625" Z="94.976119995117188" T="83354209213" />
    <Point X="212.31044006347656" Y="330.9388427734375" Z="94.692802429199219" T="83354218558" />
    <Point X="213.16555023193359" Y="328.25125122070312" Z="95.60595703125" T="83354227904" />
    <Point X="214.23187255859375" Y="325.79074096679687" Z="96.771080017089844" T="83354237249" />
    <Point X="216.00339508056641" Y="322.31533813476562" Z="97.198417663574219" T="83354246590" />
    <Point X="217.70731353759766" Y="319.0228271484375" Z="98.1678695678711" T="83354255926" />
    <Point X="218.15689849853516" Y="319.44256591796875" Z="98.398666381835938" T="83354265261" />
    <Point X="218.59100341796875" Y="318.74496459960937" Z="98.057563781738281" T="83354274597" />
    <Point X="219.17731475830078" Y="318.78726196289062" Z="98.048377990722656" T="83354283932" />
    <Point X="219.88493347167969" Y="319.58203125" Z="98.50738525390625" T="83354293273" />
    <Point X="221.01715850830078" Y="320.32278442382812" Z="98.755325317382813" T="83354302609" />
    <Point X="222.02513122558594" Y="320.02114868164062" Z="98.781814575195313" T="83354311944" />
    <Point X="223.34336853027344" Y="319.5491943359375" Z="97.725212097167969" T="83354321280" />
    <Point X="224.78047943115234" Y="322.21728515625" Z="97.709220886230469" T="83354330615" />
    <Point X="225.95015716552734" Y="324.9195556640625" Z="98.552764892578125" T="83354339951" />
    <Point X="227.06232452392578" Y="326.54269409179687" Z="99.166122436523438" T="83354349287" />
    <Point X="228.19883728027344" Y="327.30047607421875" Z="99.463455200195313" T="83354358622" />
    <Point X="229.03506469726562" Y="328.11004638671875" Z="99.6242446899414" T="83354367963" />
    <Point X="229.92811584472656" Y="329.993896484375" Z="99.557891845703125" T="83354377298" />
    <Point X="230.63775634765625" Y="331.44195556640625" Z="99.703193664550781" T="83354386634" />
    <Point X="231.31161499023437" Y="332.83868408203125" Z="99.642326354980469" T="83354395975" />
    <Point X="232.09003448486328" Y="333.93768310546875" Z="99.53521728515625" T="83354405315" />
    <Point X="232.79433441162109" Y="335.64947509765625" Z="99.2884521484375" T="83354414656" />
    <Point X="233.46971893310547" Y="336.5888671875" Z="99.15081787109375" T="83354423996" />
    <Point X="234.12531280517578" Y="336.96517944335937" Z="99.05792236328125" T="83354433342" />
    <Point X="234.74729919433594" Y="337.9144287109375" Z="98.585372924804688" T="83354442688" />
    <Point X="235.18781280517578" Y="338.54171752929687" Z="98.293319702148438" T="83354452028" />
    <Point X="235.74273681640625" Y="340.17221069335937" Z="96.533935546875" T="83354461374" />
    <Point X="236.52375793457031" Y="341.62786865234375" Z="93.963180541992188" T="83354470719" />
    <Point X="237.98690795898437" Y="340.8543701171875" Z="89.7599105834961" T="83354480065" />
    <Point X="239.34981536865234" Y="339.9290771484375" Z="85.414688110351563" T="83354489406" />
    <Point X="240.54425811767578" Y="339.66824340820312" Z="80.186393737792969" T="83354498746" />
    <Point X="242.29857635498047" Y="338.9915771484375" Z="75.1953353881836" T="83354508087" />
  </Stroke>
</Gesture>