<?xml version="1.0" encoding="utf-8" standalone="yes"?>
<Gesture Name="Custom_Points" timestamp="2015-July-28_11-04-53">
	<Stroke>
		<Point X="79.4667211408564" Y="30.354913268092" />
		<Point X="80.0849307410518" Y="33.6852515441474" />
		<Point X="80.7586828280243" Y="37.4609060024844" />
		<Point X="81.4731163677382" Y="41.7143996389115" />
		<Point X="82.6241217510508" Y="46.2481084142494" />
		<Point X="84.1589865577851" Y="51.2103693880784" />
		<Point X="85.7714616376348" Y="56.2399416021139" />
		<Point X="87.5071035246633" Y="61.5059436079721" />
		<Point X="89.602589219336" Y="67.0661978522456" />
		<Point X="91.8536710752175" Y="72.7687604896801" />
		<Point X="94.1414478283389" Y="78.520146303153" />
		<Point X="96.3406166773755" Y="84.7299549200777" />
		<Point X="98.417260524386" Y="91.0196422764248" />
		<Point X="100.485859300489" Y="97.173954081394" />
		<Point X="102.462840621218" Y="103.133293515272" />
		<Point X="104.468075579642" Y="108.856661709109" />
		<Point X="106.096657436054" Y="114.378670750781" />
		<Point X="107.5909244932" Y="119.622053819469" />
		<Point X="109.150112142604" Y="124.892235711211" />
		<Point X="110.592446885807" Y="130.160192426684" />
		<Point X="112.106451598757" Y="135.246131462226" />
		<Point X="113.619039955937" Y="140.052117680854" />
		<Point X="115.293591278489" Y="144.950132955926" />
		<Point X="117.099077784946" Y="150.108142312812" />
		<Point X="119.141046286168" Y="155.590706882476" />
		<Point X="121.169299270817" Y="161.516255001156" />
		<Point X="123.361780329458" Y="167.636043335385" />
		<Point X="125.689656921582" Y="173.740453448373" />
		<Point X="128.116752823128" Y="179.629646435184" />
		<Point X="130.610347186441" Y="185.221363446975" />
		<Point X="133.151126864883" Y="190.545989397142" />
		<Point X="135.880398210225" Y="195.177986751535" />
		<Point X="138.875152746194" Y="199.275077304328" />
		<Point X="142.041842332207" Y="202.834009943969" />
		<Point X="145.331193895523" Y="206.028159191749" />
		<Point X="148.673115407736" Y="208.904695101722" />
		<Point X="152.137747900351" Y="211.342572528908" />
		<Point X="155.597105684779" Y="213.582444804141" />
		<Point X="159.078372933954" Y="215.715329401384" />
		<Point X="162.372333376251" Y="217.551616033689" />
		<Point X="165.669080879201" Y="219.21344865618" />
		<Point X="169.373835921334" Y="220.649880169412" />
		<Point X="173.436533520748" Y="221.994570894255" />
		<Point X="177.851266642874" Y="223.567487742733" />
		<Point X="182.163733570254" Y="225.042937422263" />
		<Point X="186.322187344171" Y="226.314717596428" />
		<Point X="190.507593376232" Y="227.063196735996" />
		<Point X="194.819550398371" Y="227.568612855113" />
		<Point X="199.182878828623" Y="227.749082129614" />
		<Point X="203.338407557136" Y="227.678727202695" />
		<Point X="207.404492814505" Y="227.489146679187" />
		<Point X="211.375378233616" Y="227.10482959561" />
		<Point X="215.262657196764" Y="226.386278499688" />
		<Point X="218.943640906583" Y="225.307233462496" />
		<Point X="222.655373124146" Y="223.866068686438" />
		<Point X="226.098273832391" Y="221.944066020249" />
		<Point X="229.604156595915" Y="219.660991505867" />
		<Point X="233.14286247536" Y="217.22506308968" />
		<Point X="236.646103904447" Y="214.238560071845" />
		<Point X="240.125415592184" Y="210.705789701978" />
		<Point X="247.572860643224" Y="203.134994496219" />
		<Point X="251.437118859777" Y="199.129243897256" />
		<Point X="255.348843299647" Y="195.295988305274" />
		<Point X="259.359021806855" Y="191.517288822958" />
		<Point X="263.183517220318" Y="187.926165612296" />
		<Point X="266.998461662739" Y="184.37090772794" />
		<Point X="270.880251477672" Y="180.878732206807" />
		<Point X="274.726159706632" Y="177.243553507052" />
		<Point X="278.717277591317" Y="173.499372728947" />
		<Point X="282.864762467009" Y="169.638677691587" />
		<Point X="286.928835682468" Y="165.59719847614" />
		<Point X="291.117470593511" Y="161.572528383879" />
		<Point X="295.478955544278" Y="157.744300368288" />
		<Point X="299.850769467528" Y="154.17142955757" />
		<Point X="304.178493229224" Y="150.929352250891" />
		<Point X="308.486191067407" Y="147.929445695958" />
		<Point X="312.567649038546" Y="145.180363549732" />
		<Point X="316.552028677661" Y="142.563147952506" />
		<Point X="320.589524738966" Y="139.793204375035" />
		<Point X="324.289170878978" Y="137.18471681302" />
		<Point X="327.882045559542" Y="134.372487120712" />
		<Point X="331.442230870574" Y="131.464412424279" />
		<Point X="334.880729052171" Y="128.437617794348" />
		<Point X="338.230617838375" Y="125.34389752844" />
		<Point X="341.53384779599" Y="121.972467707061" />
		<Point X="344.858251494641" Y="118.151998703851" />
		<Point X="348.113726642402" Y="113.962666578134" />
		<Point X="351.068716236268" Y="109.76292510927" />
		<Point X="353.854428665881" Y="105.728125776153" />
		<Point X="356.433713332374" Y="101.455951014327" />
		<Point X="358.635880374562" Y="97.2189115773751" />
		<Point X="360.696235163537" Y="92.9681731897139" />
		<Point X="362.521590019095" Y="88.4801776248064" />
		<Point X="364.245629549715" Y="83.4931755728368" />
		<Point X="365.909921151754" Y="78.5030973320443" />
		<Point X="367.657962062503" Y="73.3020743440837" />
		<Point X="369.78831756332" Y="67.873604093278" />
		<Point X="372.049171476329" Y="62.2934692251641" />
		<Point X="374.636394996937" Y="56.6094177164308" />
		<Point X="377.382612446139" Y="51.1826031555464" />
		<Point X="380.412100106664" Y="45.9711109012066" />
		<Point X="383.569223445605" Y="41.0066354453045" />
		<Point X="386.88979236127" Y="36.2344648888128" />
		<Point X="390.018593200919" Y="31.4740813422818" />
		<Point X="392.813390190099" Y="27.1651559619243" />
		<Point X="395.492575427445" Y="23.3097457677151" />
		<Point X="397.753126272817" Y="19.8652326390846" />
		<Point X="399.722453359731" Y="16.7795878385347" />
		<Point X="401.473676603517" Y="14.0946859450456" />
		<Point X="402.80391760564" Y="11.981757372584" />
		<Point X="403.909178806154" Y="10.2991869889443" />
		<Point X="404.849196501751" Y="8.87454657603234" />
		<Point X="405.590737027172" Y="7.96074235018293" />
		<Point X="405.606662978863" Y="7.73139428681333" />
		<Point X="405.127790518804" Y="8.22062153956055" />
		<Point X="404.02045332406" Y="8.98777616465179" />
		<Point X="402.17381129363" Y="10.2887954147133" />
	</Stroke>
</Gesture>
