<?xml version="1.0" encoding="utf-8" standalone="yes"?>
<Gesture Name="Custom_Points" timestamp="2015-July-28_11-04-56">
	<Stroke>
		<Point X="84.1047402168422" Y="45.4496476551385" />
		<Point X="84.6097453510944" Y="49.9249108732473" />
		<Point X="85.5314823040828" Y="54.5643918441996" />
		<Point X="86.850375613202" Y="59.5384405177346" />
		<Point X="88.4571351115712" Y="64.6105719684886" />
		<Point X="90.7070402588612" Y="69.8481818363305" />
		<Point X="92.9975263097725" Y="74.7674289786007" />
		<Point X="95.2890719497734" Y="79.6799868039451" />
		<Point X="97.5210505357493" Y="84.8664763489559" />
		<Point X="99.923981981921" Y="89.9428229092962" />
		<Point X="102.22278051894" Y="95.1832902620119" />
		<Point X="104.371440020468" Y="100.365402715185" />
		<Point X="106.696095293186" Y="105.501572018905" />
		<Point X="108.972543998814" Y="110.843985535008" />
		<Point X="111.319979997931" Y="116.115612974431" />
		<Point X="113.619697902426" Y="121.511250670317" />
		<Point X="115.937937982581" Y="126.944832632435" />
		<Point X="118.193714651034" Y="132.258316853454" />
		<Point X="120.301037785623" Y="137.567381827982" />
		<Point X="122.334088528691" Y="142.772337338979" />
		<Point X="124.329045675538" Y="147.947283920084" />
		<Point X="126.299051869194" Y="152.983804474129" />
		<Point X="128.414473940659" Y="157.874527330621" />
		<Point X="130.733599339748" Y="162.3582850865" />
		<Point X="133.264098862743" Y="166.408642961023" />
		<Point X="135.92493733015" Y="170.375781635662" />
		<Point X="138.884558471569" Y="174.111637837381" />
		<Point X="142.005173359841" Y="177.739965986281" />
		<Point X="145.238706913735" Y="181.097336222391" />
		<Point X="148.496639610582" Y="184.2121752993" />
		<Point X="151.773790502352" Y="187.207433683253" />
		<Point X="155.168162833471" Y="189.755466357208" />
		<Point X="158.761298276172" Y="192.224837363191" />
		<Point X="162.501086778308" Y="194.831219961585" />
		<Point X="166.289795454329" Y="197.970030195374" />
		<Point X="169.933329927018" Y="201.155295170853" />
		<Point X="173.632834912427" Y="204.251989402891" />
		<Point X="177.378326707468" Y="207.41661357347" />
		<Point X="181.139027720347" Y="210.551669999468" />
		<Point X="185.170068163792" Y="213.506253904645" />
		<Point X="189.29258682439" Y="216.465068963822" />
		<Point X="193.317037515809" Y="219.141835486682" />
		<Point X="197.259704181596" Y="221.398866658765" />
		<Point X="201.374694428745" Y="223.454135760996" />
		<Point X="205.732224350478" Y="225.392444978004" />
		<Point X="209.98584202298" Y="226.859691650379" />
		<Point X="214.239511322318" Y="228.019952139118" />
		<Point X="218.57825177493" Y="229.002563030736" />
		<Point X="222.786230932135" Y="229.750555856071" />
		<Point X="226.957557958107" Y="229.835722202769" />
		<Point X="231.216960111914" Y="229.609888232463" />
		<Point X="235.583855384662" Y="228.757343129943" />
		<Point X="239.768174576315" Y="227.388338298774" />
		<Point X="243.949212868576" Y="225.502947352249" />
		<Point X="248.141018286607" Y="223.369168443731" />
		<Point X="252.234876399832" Y="220.964357421981" />
		<Point X="256.286109324425" Y="218.345067426599" />
		<Point X="260.26846125612" Y="215.720209822949" />
		<Point X="264.218036018717" Y="212.787112134858" />
		<Point X="268.115749386605" Y="209.67957793294" />
		<Point X="271.785226363625" Y="206.498393714934" />
		<Point X="275.300149498014" Y="203.155353124977" />
		<Point X="278.755136818153" Y="199.578623092795" />
		<Point X="282.165041281096" Y="196.042794835095" />
		<Point X="285.607753260861" Y="192.219245663423" />
		<Point X="289.05901797565" Y="188.138087461431" />
		<Point X="292.521463409528" Y="183.946829762312" />
		<Point X="296.068833254171" Y="179.50126033098" />
		<Point X="299.563742089902" Y="174.917449491449" />
		<Point X="302.87407665732" Y="170.242047435334" />
		<Point X="306.123307257651" Y="165.328170130636" />
		<Point X="309.348856355745" Y="160.053849033843" />
		<Point X="312.517954516634" Y="154.743409239658" />
		<Point X="315.622657159023" Y="149.339523865729" />
		<Point X="318.767039512542" Y="143.835567383582" />
		<Point X="321.983854830363" Y="138.203240577422" />
		<Point X="325.183448168053" Y="132.707172175392" />
		<Point X="328.519467240484" Y="127.284227906094" />
		<Point X="332.023578567206" Y="122.22486209652" />
		<Point X="335.487191860174" Y="117.636767190843" />
		<Point X="339.0801825917" Y="113.291771113643" />
		<Point X="342.618589048193" Y="108.853868963829" />
		<Point X="346.165176713196" Y="104.785261071814" />
		<Point X="349.804894327866" Y="100.759617525548" />
		<Point X="353.135756446107" Y="96.6955810089053" />
		<Point X="356.37914812013" Y="92.5861359050298" />
		<Point X="359.523226408197" Y="88.8915598501825" />
		<Point X="362.749166021508" Y="85.2615032803973" />
		<Point X="365.703397600896" Y="81.3675287959702" />
		<Point X="368.523900063975" Y="77.6109561388628" />
		<Point X="371.306537176515" Y="74.1008921663235" />
		<Point X="373.756034764207" Y="70.8550212956342" />
		<Point X="376.132152765985" Y="67.7155391763741" />
		<Point X="378.239693044006" Y="64.6224866657194" />
		<Point X="380.153807368218" Y="61.3558376871057" />
		<Point X="381.832070286139" Y="58.3482952926791" />
		<Point X="383.257734563243" Y="55.5033319978391" />
		<Point X="384.636639135749" Y="52.7597778083942" />
		<Point X="385.956146240192" Y="49.6180389880495" />
		<Point X="387.595869904829" Y="46.1598249108781" />
		<Point X="389.458956670824" Y="42.2991735213486" />
		<Point X="391.604664643571" Y="38.0944772903715" />
		<Point X="394.148964778301" Y="33.7520109280905" />
		<Point X="396.501469259156" Y="29.2416704096944" />
		<Point X="398.867047365298" Y="24.9618826303105" />
		<Point X="401.184733274329" Y="21.1949223855031" />
		<Point X="403.329414403149" Y="18.1065447526154" />
		<Point X="404.923750737162" Y="15.8311686165555" />
		<Point X="405.41487495611" Y="14.8948805787417" />
		<Point X="404.678237008151" Y="14.9189125814441" />
		<Point X="402.77712863478" Y="15.9693669407824" />
		<Point X="400.25412925054" Y="18.0985348653016" />
		<Point X="397.024561818706" Y="21.0566042606465" />
	</Stroke>
</Gesture>
