<?xml version="1.0" encoding="utf-8"?>
<Gesture xmlns:xsd="http://www.w3.org/2001/XMLSchema" xmlns:xsi="http://www.w3.org/2001/XMLSchema-instance">
  <Name>Sine</Name>
  <Subject>Willian</Subject>
  <Iteration>4</Iteration>
  <InputType>Leap Motion</InputType>
  <Speed>MEDIUM</Speed>
  <time>1056053</time>
  <NumPts>114</NumPts>
  <Stroke Index="1">
    <Point X="2.3144378662109375" Y="324.69195556640625" Z="39.944160461425781" T="83925892407" />
    <Point X="1.9635391235351563" Y="324.4306640625" Z="40.084785461425781" T="83925901752" />
    <Point X="1.8709182739257813" Y="324.52291870117187" Z="39.994350433349609" T="83925911098" />
    <Point X="1.7809600830078125" Y="324.38845825195312" Z="39.949142456054687" T="83925920444" />
    <Point X="1.5045928955078125" Y="324.10250854492187" Z="39.723114013671875" T="83925929789" />
    <Point X="1.03436279296875" Y="323.52859497070312" Z="39.205734252929688" T="83925939135" />
    <Point X="0.53199005126953125" Y="322.06973266601562" Z="38.405193328857422" T="83925948480" />
    <Point X="0.15810394287109375" Y="320.07705688476562" Z="37.741645812988281" T="83925957826" />
    <Point X="0" Y="318.7288818359375" Z="37.276424407958984" T="83925967172" />
    <Point X="0.4777679443359375" Y="314.71841430664062" Z="37.594200134277344" T="83925976517" />
    <Point X="0.4981231689453125" Y="311.058837890625" Z="38.211036682128906" T="83925985863" />
    <Point X="0.28436279296875" Y="306.6195068359375" Z="39.203636169433594" T="83925995208" />
    <Point X="0.10015869140625" Y="302.48419189453125" Z="39.9259147644043" T="83926004554" />
    <Point X="0.00159454345703125" Y="298.76239013671875" Z="39.965106964111328" T="83926013900" />
    <Point X="0.28905487060546875" Y="294.89892578125" Z="40.230495452880859" T="83926023245" />
    <Point X="0.58931732177734375" Y="291.0572509765625" Z="40.696979522705078" T="83926032591" />
    <Point X="1.49102783203125" Y="287.90863037109375" Z="41.279788970947266" T="83926041936" />
    <Point X="2.12939453125" Y="284.79153442382812" Z="41.851154327392578" T="83926051282" />
    <Point X="2.619415283203125" Y="283.05807495117187" Z="42.132015228271484" T="83926060628" />
    <Point X="3.900665283203125" Y="280.6904296875" Z="42.5319938659668" T="83926069973" />
    <Point X="4.7857589721679687" Y="277.84817504882812" Z="43.098320007324219" T="83926079319" />
    <Point X="6.1781387329101563" Y="275.13461303710937" Z="43.500572204589844" T="83926088664" />
    <Point X="6.9193267822265625" Y="270.45343017578125" Z="43.575119018554688" T="83926098010" />
    <Point X="7.6171340942382812" Y="266.92672729492187" Z="44.475955963134766" T="83926107356" />
    <Point X="8.0478363037109375" Y="263.83709716796875" Z="45.640476226806641" T="83926116701" />
    <Point X="9.135284423828125" Y="260.6810302734375" Z="45.502353668212891" T="83926126047" />
    <Point X="9.9562606811523437" Y="257.62213134765625" Z="45.772216796875" T="83926135392" />
    <Point X="11.057571411132812" Y="255.06716918945312" Z="45.552825927734375" T="83926144738" />
    <Point X="12.410331726074219" Y="252.10604858398437" Z="45.744113922119141" T="83926154084" />
    <Point X="14.101104736328125" Y="248.00579833984375" Z="46.054862976074219" T="83926163429" />
    <Point X="15.089809417724609" Y="244.03274536132812" Z="45.863761901855469" T="83926172775" />
    <Point X="16.493152618408203" Y="240.08639526367187" Z="45.645160675048828" T="83926182120" />
    <Point X="17.933444976806641" Y="236.98849487304688" Z="45.9248046875" T="83926191466" />
    <Point X="19.387630462646484" Y="234.427734375" Z="46.012321472167969" T="83926200812" />
    <Point X="20.774078369140625" Y="230.93661499023437" Z="46.017890930175781" T="83926210157" />
    <Point X="21.932826995849609" Y="228.70196533203125" Z="45.549171447753906" T="83926219503" />
    <Point X="22.928535461425781" Y="226.67135620117187" Z="45.920772552490234" T="83926228848" />
    <Point X="24.165615081787109" Y="225.20025634765625" Z="45.867477416992188" T="83926238194" />
    <Point X="25.101619720458984" Y="223.839111328125" Z="45.926254272460938" T="83926247540" />
    <Point X="26.386283874511719" Y="223.67050170898437" Z="45.899822235107422" T="83926256885" />
    <Point X="27.796829223632813" Y="222.7574462890625" Z="46.467018127441406" T="83926266231" />
    <Point X="29.089752197265625" Y="222.13241577148437" Z="46.623878479003906" T="83926275576" />
    <Point X="30.655941009521484" Y="221.60504150390625" Z="46.543037414550781" T="83926284922" />
    <Point X="31.745658874511719" Y="221.33453369140625" Z="46.5106086730957" T="83926294268" />
    <Point X="33.834060668945313" Y="222.02984619140625" Z="46.103122711181641" T="83926303613" />
    <Point X="35.740936279296875" Y="222.55630493164062" Z="45.763710021972656" T="83926312959" />
    <Point X="37.183731079101563" Y="223.02639770507812" Z="45.373939514160156" T="83926322304" />
    <Point X="38.947799682617188" Y="224.39959716796875" Z="44.97076416015625" T="83926331650" />
    <Point X="40.410072326660156" Y="225.69757080078125" Z="44.898174285888672" T="83926340996" />
    <Point X="42.5149040222168" Y="228.64556884765625" Z="45.154453277587891" T="83926350341" />
    <Point X="44.795581817626953" Y="231.97335815429687" Z="43.519062042236328" T="83926359687" />
    <Point X="46.219978332519531" Y="233.60354614257812" Z="43.001270294189453" T="83926369032" />
    <Point X="47.156038284301758" Y="234.8050537109375" Z="42.704963684082031" T="83926378378" />
    <Point X="48.608400344848633" Y="237.24627685546875" Z="42.525554656982422" T="83926387724" />
    <Point X="50.058792114257813" Y="241.08984375" Z="41.6488151550293" T="83926397069" />
    <Point X="51.741268157958984" Y="244.579345703125" Z="41.215354919433594" T="83926406415" />
    <Point X="53.377099990844727" Y="249.21414184570312" Z="41.031913757324219" T="83926415760" />
    <Point X="54.966447830200195" Y="254.22769165039062" Z="40.883499145507812" T="83926425106" />
    <Point X="56.12809944152832" Y="257.89901733398437" Z="40.347568511962891" T="83926434452" />
    <Point X="57.361749649047852" Y="262.59396362304687" Z="39.5159797668457" T="83926443797" />
    <Point X="58.602207183837891" Y="265.56625366210937" Z="38.871337890625" T="83926453143" />
    <Point X="59.45661735534668" Y="270.43093872070312" Z="38.665069580078125" T="83926462488" />
    <Point X="60.431585311889648" Y="274.73590087890625" Z="37.891704559326172" T="83926471834" />
    <Point X="61.464912414550781" Y="280.43280029296875" Z="37.375534057617188" T="83926481180" />
    <Point X="62.354887008666992" Y="285.62466430664062" Z="37.220951080322266" T="83926490525" />
    <Point X="62.730422019958496" Y="289.20370483398438" Z="37.047092437744141" T="83926499871" />
    <Point X="63.58830738067627" Y="294.00323486328125" Z="36.398609161376953" T="83926509216" />
    <Point X="64.30998420715332" Y="299.43267822265625" Z="36.231143951416016" T="83926518562" />
    <Point X="64.898214340209961" Y="305.47076416015625" Z="35.754035949707031" T="83926527908" />
    <Point X="65.555177688598633" Y="311.53973388671875" Z="35.044708251953125" T="83926537253" />
    <Point X="66.180997848510742" Y="316.41702270507812" Z="34.620021820068359" T="83926546599" />
    <Point X="67.3336706161499" Y="321.09921264648437" Z="33.969215393066406" T="83926555944" />
    <Point X="68.165413856506348" Y="325.91864013671875" Z="33.417350769042969" T="83926565290" />
    <Point X="68.130267143249512" Y="330.31695556640625" Z="33.801506042480469" T="83926574636" />
    <Point X="68.147254943847656" Y="333.79428100585937" Z="33.095237731933594" T="83926583981" />
    <Point X="69.441802024841309" Y="338.10690307617187" Z="32.244976043701172" T="83926593327" />
    <Point X="70.2217903137207" Y="343.89889526367188" Z="31.683942794799805" T="83926602672" />
    <Point X="70.782093524932861" Y="348.08808898925781" Z="31.715175628662109" T="83926612018" />
    <Point X="71.740736484527588" Y="350.83438110351562" Z="30.509065628051758" T="83926621364" />
    <Point X="73.249599933624268" Y="353.57609558105469" Z="29.640911102294922" T="83926630709" />
    <Point X="74.578006744384766" Y="357.35496520996094" Z="29.144817352294922" T="83926640055" />
    <Point X="76.359391450881958" Y="361.21830749511719" Z="28.605255126953125" T="83926649400" />
    <Point X="78.196642637252808" Y="364.32258605957031" Z="28.47926139831543" T="83926658746" />
    <Point X="79.76835823059082" Y="366.461669921875" Z="28.64630126953125" T="83926668092" />
    <Point X="81.1455237865448" Y="368.27278137207031" Z="28.629177093505859" T="83926677437" />
    <Point X="82.817233562469482" Y="370.40788269042969" Z="28.134975433349609" T="83926686783" />
    <Point X="84.45103120803833" Y="372.01356506347656" Z="27.924480438232422" T="83926696128" />
    <Point X="86.392559051513672" Y="373.2420654296875" Z="27.702552795410156" T="83926705474" />
    <Point X="88.218875885009766" Y="374.35305786132812" Z="27.595895767211914" T="83926714820" />
    <Point X="90.243650436401367" Y="375.26052856445312" Z="27.365081787109375" T="83926724165" />
    <Point X="92.080612182617188" Y="376.02340698242187" Z="26.799152374267578" T="83926733511" />
    <Point X="93.78148078918457" Y="376.46580505371094" Z="26.44365119934082" T="83926742856" />
    <Point X="95.38433837890625" Y="376.66278076171875" Z="26.096656799316406" T="83926752202" />
    <Point X="97.132009506225586" Y="376.54254150390625" Z="25.873258590698242" T="83926761548" />
    <Point X="99.320344924926758" Y="375.46846008300781" Z="25.811437606811523" T="83926770893" />
    <Point X="100.71182632446289" Y="373.39511108398437" Z="26.222566604614258" T="83926780239" />
    <Point X="102.53211975097656" Y="371.06132507324219" Z="26.568790435791016" T="83926789584" />
    <Point X="104.16216278076172" Y="369.10333251953125" Z="26.501684188842773" T="83926798930" />
    <Point X="105.41979789733887" Y="365.25532531738281" Z="25.842855453491211" T="83926808276" />
    <Point X="106.49700736999512" Y="361.55337524414062" Z="25.130863189697266" T="83926817621" />
    <Point X="107.45801544189453" Y="358.4476318359375" Z="23.667444229125977" T="83926826967" />
    <Point X="108.37595367431641" Y="353.98316955566406" Z="21.566326141357422" T="83926836312" />
    <Point X="108.86613273620605" Y="348.92820739746094" Z="19.566837310791016" T="83926845658" />
    <Point X="108.80143356323242" Y="344.28546142578125" Z="18.768411636352539" T="83926855004" />
    <Point X="108.64850044250488" Y="340.72711181640625" Z="16.246431350708008" T="83926864349" />
    <Point X="110.24273300170898" Y="333.03524780273437" Z="14.33530330657959" T="83926873695" />
    <Point X="111.41492462158203" Y="326.0882568359375" Z="13.27198600769043" T="83926883040" />
    <Point X="112.19000625610352" Y="320.33837890625" Z="12.994719505310059" T="83926892386" />
    <Point X="113.05861282348633" Y="313.93215942382812" Z="13.221598625183105" T="83926901732" />
    <Point X="113.84637069702148" Y="308.39312744140625" Z="13.573698997497559" T="83926911077" />
    <Point X="114.85309600830078" Y="303.15512084960937" Z="13.644304275512695" T="83926920423" />
    <Point X="114.0070915222168" Y="297.68402099609375" Z="13.977815628051758" T="83926929768" />
    <Point X="113.09091186523437" Y="293.02780151367187" Z="11.432190895080566" T="83926939114" />
    <Point X="111.59358596801758" Y="288.63156127929687" Z="8.2864284515380859" T="83926948460" />
  </Stroke>
</Gesture>